{
    "MaxX": 1400,
    "Obstacles": [
        {
            "Position": {
                "X-pos": 1,
                "Y-pos": 1
            },
            "Obstacle Speed": 6,
            "Obstacle Direction": "right",
            "Decider": 0.4688628079718331
        },
        {
            "Position": {
                "X-pos": 2,
                "Y-pos": 10
            },
            "Obstacle Speed": 2,
            "Obstacle Direction": "right",
            "Decider": 0.11665619223966561
        }
    ],
    "MaxY": 600,
    "ticker": 0,
    "Points": [{
        "x": 334,
        "y": 155
    }],
    "Score": 0,
    "PlayerCharacter": {
        "X-pos": 0,
        "Y-pos": 580
    },
    "Ended": false,
    "CanSpawnObstacles": true,
    "Seconds passed": 0,
    "Gravity": {
        "Grav Direction": -1,
        "Gravitating": false
    },
    "Decider": 0
}